README.md
setup.py
ods/__init__.py
ods/ods.py
ods.egg-info/PKG-INFO
ods.egg-info/SOURCES.txt
ods.egg-info/dependency_links.txt
ods.egg-info/requires.txt
ods.egg-info/top_level.txt
ods/spark_cluster/__init__.py
ods/spark_cluster/spark_cluster.py
tests/__init__.py
tests/test_ods.py
tests/test_spark.py