Metadata-Version: 2.1
Name: ods
Version: 0.0.2
Summary: Python client library for Staroid cloud platform
Home-page: https://github.com/open-datastudio/ods
Author: Open Data Studio
Author-email: moon@staroid.com
License: MIT
Platform: UNKNOWN
Classifier: Development Status :: 5 - Production/Stable
Classifier: Intended Audience :: Developers
Classifier: Topic :: Software Development :: Libraries
Classifier: Programming Language :: Python :: 3.6
Classifier: Programming Language :: Python :: 3.7
Classifier: Programming Language :: Python :: 3.8
Classifier: License :: OSI Approved :: MIT License
Classifier: Operating System :: OS Independent
Requires-Python: >=3.6
